[1,["44M6GmCttMXZ99O1wcTwwt@6c48a","4f7rv0Z/hIvZMBs/ft5u2F@6c48a","57tQs+GCNGlIIbEsPYwJJ7@6c48a","61naxKKXNFaoRQXuugRjEX@6c48a","698Ug9EW9LqomfhegicODD@6c48a","6dkugdVExKrLD1GFIlrezI@6c48a","91KZQC2XRJ+qHYLB40/HJw@6c48a","95AmFS5PtPrYxHj5RKKAOu@6c48a","a6pQyltx1IBq4s4o2TVrpR@6c48a","a92OebKXhOUoO25nh0euMk@6c48a","baPjfHp61FELVgWXlyoZk5@6c48a","c1jJ+Qrs9M57KGMBx3ZrE2@6c48a","f0KBfs2rdMGZS8UauDBbAK@6c48a","f2O/XSqZlArJ0TxJYIWdYJ@6c48a","fc2e6nKFBDO6A5X1XW2xJ1@6c48a","fdCTXeFIpFbq+Oa9DODzJ5@6c48a"],["_textureSource"],["cc.SpriteFrame"],0,[[[{"name":"monster4_06","rect":{"x":0,"y":8,"width":109,"height":113},"offset":{"x":-0.5,"y":-3},"originalSize":{"width":110,"height":123},"rotated":false,"capInsets":[0,0,0,0],"vertices":{"rawPosition":[-54.5,-56.5,0,54.5,-56.5,0,-54.5,56.5,0,54.5,56.5,0],"indexes":[0,1,2,2,1,3],"uv":[0,115,109,115,0,2,109,2],"nuv":[0,0.016260162601626018,0.990909090909091,0.016260162601626018,0,0.9349593495934959,0.990909090909091,0.9349593495934959],"minPos":{"x":-54.5,"y":-56.5,"z":0},"maxPos":{"x":54.5,"y":56.5,"z":0}},"packable":true,"pixelsToUnit":100,"pivot":{"x":0.5,"y":0.5},"meshType":0}],[0],0,[0],[0],[0]],[[{"name":"monster4_14","rect":{"x":1,"y":0,"width":107,"height":122},"offset":{"x":-0.5,"y":0.5},"originalSize":{"width":110,"height":123},"rotated":false,"capInsets":[0,0,0,0],"vertices":{"rawPosition":[-53.5,-61,0,53.5,-61,0,-53.5,61,0,53.5,61,0],"indexes":[0,1,2,2,1,3],"uv":[1,123,108,123,1,1,108,1],"nuv":[0.00909090909090909,0.008130081300813009,0.9818181818181818,0.008130081300813009,0.00909090909090909,1,0.9818181818181818,1],"minPos":{"x":-53.5,"y":-61,"z":0},"maxPos":{"x":53.5,"y":61,"z":0}},"packable":true,"pixelsToUnit":100,"pivot":{"x":0.5,"y":0.5},"meshType":0}],[0],0,[0],[0],[1]],[[{"name":"monster4_15","rect":{"x":0,"y":1,"width":108,"height":121},"offset":{"x":-1,"y":0},"originalSize":{"width":110,"height":123},"rotated":false,"capInsets":[0,0,0,0],"vertices":{"rawPosition":[-54,-60.5,0,54,-60.5,0,-54,60.5,0,54,60.5,0],"indexes":[0,1,2,2,1,3],"uv":[0,122,108,122,0,1,108,1],"nuv":[0,0.008130081300813009,0.9818181818181818,0.008130081300813009,0,0.991869918699187,0.9818181818181818,0.991869918699187],"minPos":{"x":-54,"y":-60.5,"z":0},"maxPos":{"x":54,"y":60.5,"z":0}},"packable":true,"pixelsToUnit":100,"pivot":{"x":0.5,"y":0.5},"meshType":0}],[0],0,[0],[0],[2]],[[{"name":"monster4_08","rect":{"x":0,"y":7,"width":109,"height":115},"offset":{"x":-0.5,"y":-3},"originalSize":{"width":110,"height":123},"rotated":false,"capInsets":[0,0,0,0],"vertices":{"rawPosition":[-54.5,-57.5,0,54.5,-57.5,0,-54.5,57.5,0,54.5,57.5,0],"indexes":[0,1,2,2,1,3],"uv":[0,116,109,116,0,1,109,1],"nuv":[0,0.008130081300813009,0.990909090909091,0.008130081300813009,0,0.943089430894309,0.990909090909091,0.943089430894309],"minPos":{"x":-54.5,"y":-57.5,"z":0},"maxPos":{"x":54.5,"y":57.5,"z":0}},"packable":true,"pixelsToUnit":100,"pivot":{"x":0.5,"y":0.5},"meshType":0}],[0],0,[0],[0],[3]],[[{"name":"monster4_04","rect":{"x":0,"y":7,"width":109,"height":114},"offset":{"x":-0.5,"y":-2.5},"originalSize":{"width":110,"height":123},"rotated":false,"capInsets":[0,0,0,0],"vertices":{"rawPosition":[-54.5,-57,0,54.5,-57,0,-54.5,57,0,54.5,57,0],"indexes":[0,1,2,2,1,3],"uv":[0,116,109,116,0,2,109,2],"nuv":[0,0.016260162601626018,0.990909090909091,0.016260162601626018,0,0.943089430894309,0.990909090909091,0.943089430894309],"minPos":{"x":-54.5,"y":-57,"z":0},"maxPos":{"x":54.5,"y":57,"z":0}},"packable":true,"pixelsToUnit":100,"pivot":{"x":0.5,"y":0.5},"meshType":0}],[0],0,[0],[0],[4]],[[{"name":"monster4_05","rect":{"x":1,"y":8,"width":108,"height":113},"offset":{"x":0,"y":-3},"originalSize":{"width":110,"height":123},"rotated":false,"capInsets":[0,0,0,0],"vertices":{"rawPosition":[-54,-56.5,0,54,-56.5,0,-54,56.5,0,54,56.5,0],"indexes":[0,1,2,2,1,3],"uv":[1,115,109,115,1,2,109,2],"nuv":[0.00909090909090909,0.016260162601626018,0.990909090909091,0.016260162601626018,0.00909090909090909,0.9349593495934959,0.990909090909091,0.9349593495934959],"minPos":{"x":-54,"y":-56.5,"z":0},"maxPos":{"x":54,"y":56.5,"z":0}},"packable":true,"pixelsToUnit":100,"pivot":{"x":0.5,"y":0.5},"meshType":0}],[0],0,[0],[0],[5]],[[{"name":"monster4_09","rect":{"x":1,"y":6,"width":108,"height":116},"offset":{"x":0,"y":-2.5},"originalSize":{"width":110,"height":123},"rotated":false,"capInsets":[0,0,0,0],"vertices":{"rawPosition":[-54,-58,0,54,-58,0,-54,58,0,54,58,0],"indexes":[0,1,2,2,1,3],"uv":[1,117,109,117,1,1,109,1],"nuv":[0.00909090909090909,0.008130081300813009,0.990909090909091,0.008130081300813009,0.00909090909090909,0.9512195121951219,0.990909090909091,0.9512195121951219],"minPos":{"x":-54,"y":-58,"z":0},"maxPos":{"x":54,"y":58,"z":0}},"packable":true,"pixelsToUnit":100,"pivot":{"x":0.5,"y":0.5},"meshType":0}],[0],0,[0],[0],[6]],[[{"name":"monster4_11","rect":{"x":1,"y":3,"width":108,"height":119},"offset":{"x":0,"y":-1},"originalSize":{"width":110,"height":123},"rotated":false,"capInsets":[0,0,0,0],"vertices":{"rawPosition":[-54,-59.5,0,54,-59.5,0,-54,59.5,0,54,59.5,0],"indexes":[0,1,2,2,1,3],"uv":[1,120,109,120,1,1,109,1],"nuv":[0.00909090909090909,0.008130081300813009,0.990909090909091,0.008130081300813009,0.00909090909090909,0.975609756097561,0.990909090909091,0.975609756097561],"minPos":{"x":-54,"y":-59.5,"z":0},"maxPos":{"x":54,"y":59.5,"z":0}},"packable":true,"pixelsToUnit":100,"pivot":{"x":0.5,"y":0.5},"meshType":0}],[0],0,[0],[0],[7]],[[{"name":"monster4_01","rect":{"x":0,"y":3,"width":109,"height":118},"offset":{"x":-0.5,"y":-0.5},"originalSize":{"width":110,"height":123},"rotated":false,"capInsets":[0,0,0,0],"vertices":{"rawPosition":[-54.5,-59,0,54.5,-59,0,-54.5,59,0,54.5,59,0],"indexes":[0,1,2,2,1,3],"uv":[0,120,109,120,0,2,109,2],"nuv":[0,0.016260162601626018,0.990909090909091,0.016260162601626018,0,0.975609756097561,0.990909090909091,0.975609756097561],"minPos":{"x":-54.5,"y":-59,"z":0},"maxPos":{"x":54.5,"y":59,"z":0}},"packable":true,"pixelsToUnit":100,"pivot":{"x":0.5,"y":0.5},"meshType":0}],[0],0,[0],[0],[8]],[[{"name":"monster4_07","rect":{"x":1,"y":8,"width":108,"height":113},"offset":{"x":0,"y":-3},"originalSize":{"width":110,"height":123},"rotated":false,"capInsets":[0,0,0,0],"vertices":{"rawPosition":[-54,-56.5,0,54,-56.5,0,-54,56.5,0,54,56.5,0],"indexes":[0,1,2,2,1,3],"uv":[1,115,109,115,1,2,109,2],"nuv":[0.00909090909090909,0.016260162601626018,0.990909090909091,0.016260162601626018,0.00909090909090909,0.9349593495934959,0.990909090909091,0.9349593495934959],"minPos":{"x":-54,"y":-56.5,"z":0},"maxPos":{"x":54,"y":56.5,"z":0}},"packable":true,"pixelsToUnit":100,"pivot":{"x":0.5,"y":0.5},"meshType":0}],[0],0,[0],[0],[9]],[[{"name":"monster4_00","rect":{"x":0,"y":1,"width":107,"height":121},"offset":{"x":-1.5,"y":0},"originalSize":{"width":110,"height":123},"rotated":false,"capInsets":[0,0,0,0],"vertices":{"rawPosition":[-53.5,-60.5,0,53.5,-60.5,0,-53.5,60.5,0,53.5,60.5,0],"indexes":[0,1,2,2,1,3],"uv":[0,122,107,122,0,1,107,1],"nuv":[0,0.008130081300813009,0.9727272727272728,0.008130081300813009,0,0.991869918699187,0.9727272727272728,0.991869918699187],"minPos":{"x":-53.5,"y":-60.5,"z":0},"maxPos":{"x":53.5,"y":60.5,"z":0}},"packable":true,"pixelsToUnit":100,"pivot":{"x":0.5,"y":0.5},"meshType":0}],[0],0,[0],[0],[10]],[[{"name":"monster4_13","rect":{"x":1,"y":1,"width":108,"height":121},"offset":{"x":0,"y":0},"originalSize":{"width":110,"height":123},"rotated":false,"capInsets":[0,0,0,0],"vertices":{"rawPosition":[-54,-60.5,0,54,-60.5,0,-54,60.5,0,54,60.5,0],"indexes":[0,1,2,2,1,3],"uv":[1,122,109,122,1,1,109,1],"nuv":[0.00909090909090909,0.008130081300813009,0.990909090909091,0.008130081300813009,0.00909090909090909,0.991869918699187,0.990909090909091,0.991869918699187],"minPos":{"x":-54,"y":-60.5,"z":0},"maxPos":{"x":54,"y":60.5,"z":0}},"packable":true,"pixelsToUnit":100,"pivot":{"x":0.5,"y":0.5},"meshType":0}],[0],0,[0],[0],[11]],[[{"name":"monster4_03","rect":{"x":1,"y":6,"width":109,"height":115},"offset":{"x":0.5,"y":-2},"originalSize":{"width":110,"height":123},"rotated":false,"capInsets":[0,0,0,0],"vertices":{"rawPosition":[-54.5,-57.5,0,54.5,-57.5,0,-54.5,57.5,0,54.5,57.5,0],"indexes":[0,1,2,2,1,3],"uv":[1,117,110,117,1,2,110,2],"nuv":[0.00909090909090909,0.016260162601626018,1,0.016260162601626018,0.00909090909090909,0.9512195121951219,1,0.9512195121951219],"minPos":{"x":-54.5,"y":-57.5,"z":0},"maxPos":{"x":54.5,"y":57.5,"z":0}},"packable":true,"pixelsToUnit":100,"pivot":{"x":0.5,"y":0.5},"meshType":0}],[0],0,[0],[0],[12]],[[{"name":"monster4_10","rect":{"x":1,"y":5,"width":108,"height":117},"offset":{"x":0,"y":-2},"originalSize":{"width":110,"height":123},"rotated":false,"capInsets":[0,0,0,0],"vertices":{"rawPosition":[-54,-58.5,0,54,-58.5,0,-54,58.5,0,54,58.5,0],"indexes":[0,1,2,2,1,3],"uv":[1,118,109,118,1,1,109,1],"nuv":[0.00909090909090909,0.008130081300813009,0.990909090909091,0.008130081300813009,0.00909090909090909,0.959349593495935,0.990909090909091,0.959349593495935],"minPos":{"x":-54,"y":-58.5,"z":0},"maxPos":{"x":54,"y":58.5,"z":0}},"packable":true,"pixelsToUnit":100,"pivot":{"x":0.5,"y":0.5},"meshType":0}],[0],0,[0],[0],[13]],[[{"name":"monster4_12","rect":{"x":1,"y":2,"width":108,"height":120},"offset":{"x":0,"y":-0.5},"originalSize":{"width":110,"height":123},"rotated":false,"capInsets":[0,0,0,0],"vertices":{"rawPosition":[-54,-60,0,54,-60,0,-54,60,0,54,60,0],"indexes":[0,1,2,2,1,3],"uv":[1,121,109,121,1,1,109,1],"nuv":[0.00909090909090909,0.008130081300813009,0.990909090909091,0.008130081300813009,0.00909090909090909,0.983739837398374,0.990909090909091,0.983739837398374],"minPos":{"x":-54,"y":-60,"z":0},"maxPos":{"x":54,"y":60,"z":0}},"packable":true,"pixelsToUnit":100,"pivot":{"x":0.5,"y":0.5},"meshType":0}],[0],0,[0],[0],[14]],[[{"name":"monster4_02","rect":{"x":0,"y":4,"width":109,"height":117},"offset":{"x":-0.5,"y":-1},"originalSize":{"width":110,"height":123},"rotated":false,"capInsets":[0,0,0,0],"vertices":{"rawPosition":[-54.5,-58.5,0,54.5,-58.5,0,-54.5,58.5,0,54.5,58.5,0],"indexes":[0,1,2,2,1,3],"uv":[0,119,109,119,0,2,109,2],"nuv":[0,0.016260162601626018,0.990909090909091,0.016260162601626018,0,0.967479674796748,0.990909090909091,0.967479674796748],"minPos":{"x":-54.5,"y":-58.5,"z":0},"maxPos":{"x":54.5,"y":58.5,"z":0}},"packable":true,"pixelsToUnit":100,"pivot":{"x":0.5,"y":0.5},"meshType":0}],[0],0,[0],[0],[15]]]]
